CHANGELOG.md
MANIFEST.in
README.md
README.txt
requirements.txt
setup.py
bin/sokery
sokery/__init__.py
sokery/__main__.py
sokery/client.py
sokery/loop.py
sokery.egg-info/PKG-INFO
sokery.egg-info/SOURCES.txt
sokery.egg-info/dependency_links.txt
sokery.egg-info/requires.txt
sokery.egg-info/top_level.txt
sokery/utils/__init__.py
sokery/utils/types.py
sokery/web/__init__.py
sokery/web/admin.py
sokery/web/app.py
sokery/web/proxy.py
sokery/web/tcp.py
sokery/web/views/index.html
sokery/web/views/ng.js