Metadata-Version: 1.0
Name: sokery
Version: 0.3.1.post2
Summary: Socket testing with web interface
Home-page: https://github.com/gamikun/sokery
Author: Gamaliel Espinoza
Author-email: gamaliel.espinoza@gmail.com
License: UNKNOWN
Keywords: sokery
Platform: UNKNOWN
